controllers/operations.py
models/calculator.py
schemas/operation_request.py
calculadora_fastapi_atividadeps-0.1.3.dist-info/METADATA
calculadora_fastapi_atividadeps-0.1.3.dist-info/WHEEL
calculadora_fastapi_atividadeps-0.1.3.dist-info/top_level.txt
calculadora_fastapi_atividadeps-0.1.3.dist-info/RECORD
