Metadata-Version: 2.4
Name: calculadora-fastapi-atividadeps
Version: 0.1.3
Summary: Uma API de calculadora simples usando FastAPI
Author-email: ryanlimap <pesagaz@hotmail.com>
License-Expression: MIT
Classifier: Programming Language :: Python :: 3
Classifier: Operating System :: OS Independent
Requires-Python: >=3.7
Requires-Dist: fastapi>=0.100
Requires-Dist: uvicorn[standard]>=0.22
